shreddit/__init__.py
shreddit/app.py
shreddit/praw.ini.example
shreddit/util.py
shreddit/shredder.py
shreddit/shreddit.yml.example
shreddit-6.0.7.dist-info/DESCRIPTION.rst
shreddit-6.0.7.dist-info/metadata.json
shreddit-6.0.7.dist-info/METADATA
shreddit-6.0.7.dist-info/top_level.txt
shreddit-6.0.7.dist-info/RECORD
shreddit-6.0.7.dist-info/WHEEL
shreddit-6.0.7.dist-info/entry_points.txt
