Metadata-Version: 2.0
Name: shreddit
Version: 6.0.7
Summary: Remove your comment history on Reddit as deleting an account does not do so.
Home-page: https://github.com/x89/Shreddit
Author: David John
Author-email: david@vaunt.eu
License: FreeBSD License
Platform: UNKNOWN
Classifier: Development Status :: 4 - Beta
Classifier: Intended Audience :: End Users/Desktop
Classifier: License :: OSI Approved :: BSD License
Classifier: Programming Language :: Python
Requires-Dist: arrow
Requires-Dist: backports-abc
Requires-Dist: praw (>=4)
Requires-Dist: PyYAML
Requires-Dist: requests
Requires-Dist: six
Requires-Dist: tornado
